dapr/__init__.pyi
dapr/py.typed
dapr/actor/__init__.py
dapr/actor/actor_interface.py
dapr/actor/id.py
dapr/actor/client/__init__.py
dapr/actor/client/proxy.py
dapr/actor/runtime/__init__.py
dapr/actor/runtime/_call_type.py
dapr/actor/runtime/_method_context.py
dapr/actor/runtime/_reminder_data.py
dapr/actor/runtime/_state_provider.py
dapr/actor/runtime/_timer_data.py
dapr/actor/runtime/_type_information.py
dapr/actor/runtime/_type_utils.py
dapr/actor/runtime/actor.py
dapr/actor/runtime/config.py
dapr/actor/runtime/context.py
dapr/actor/runtime/manager.py
dapr/actor/runtime/method_dispatcher.py
dapr/actor/runtime/mock_actor.py
dapr/actor/runtime/mock_state_manager.py
dapr/actor/runtime/reentrancy_context.py
dapr/actor/runtime/remindable.py
dapr/actor/runtime/runtime.py
dapr/actor/runtime/state_change.py
dapr/actor/runtime/state_manager.py
dapr/aio/clients/__init__.py
dapr/aio/clients/health.py
dapr/aio/clients/grpc/__init__.py
dapr/aio/clients/grpc/_request.py
dapr/aio/clients/grpc/_response.py
dapr/aio/clients/grpc/client.py
dapr/aio/clients/grpc/interceptors.py
dapr/aio/clients/grpc/subscription.py
dapr/clients/__init__.py
dapr/clients/_constants.py
dapr/clients/base.py
dapr/clients/exceptions.py
dapr/clients/health.py
dapr/clients/retry.py
dapr/clients/grpc/__init__.py
dapr/clients/grpc/_conversation_helpers.py
dapr/clients/grpc/_crypto.py
dapr/clients/grpc/_helpers.py
dapr/clients/grpc/_jobs.py
dapr/clients/grpc/_request.py
dapr/clients/grpc/_response.py
dapr/clients/grpc/_state.py
dapr/clients/grpc/client.py
dapr/clients/grpc/conversation.py
dapr/clients/grpc/interceptors.py
dapr/clients/grpc/subscription.py
dapr/clients/http/__init__.py
dapr/clients/http/client.py
dapr/clients/http/conf.py
dapr/clients/http/dapr_actor_http_client.py
dapr/clients/http/dapr_invocation_http_client.py
dapr/clients/http/helpers.py
dapr/common/pubsub/subscription.py
dapr/conf/__init__.py
dapr/conf/global_settings.py
dapr/conf/helpers.py
dapr/proto/__init__.py
dapr_dev-1.16.0.dev60.dist-info/licenses/LICENSE
dapr_dev-1.16.0.dev60.dist-info/METADATA
dapr_dev-1.16.0.dev60.dist-info/WHEEL
dapr_dev-1.16.0.dev60.dist-info/top_level.txt
dapr_dev-1.16.0.dev60.dist-info/RECORD
